sysfsgpio/__init__.py
sysfsgpio/pin.py
sysfsgpio/utils.py
sysfsgpio/version.py
sysfsgpio/resources/gpio-exporter.service
sysfsgpio/resources/gpio.rules
sysfsgpio-0.3.0.dist-info/LICENSE
sysfsgpio-0.3.0.dist-info/METADATA
sysfsgpio-0.3.0.dist-info/WHEEL
sysfsgpio-0.3.0.dist-info/entry_points.txt
sysfsgpio-0.3.0.dist-info/top_level.txt
sysfsgpio-0.3.0.dist-info/RECORD
