Metadata-Version: 2.1
Name: sysfsgpio
Version: 0.3.0
Summary: Sysfs GPIO utility
Home-page: https://gitlab.com/kkubkowski/sysfsgpiolib
Author: Kacper Kubkowski
Author-email: kkubkowski@gmail.com
License: UNKNOWN
Platform: UNKNOWN
Classifier: Programming Language :: Python :: 3
Classifier: License :: OSI Approved :: MIT License
Classifier: Operating System :: POSIX :: Linux
